printlib/__init__.py
printlib/output.py
print_libs-0.1.0.dist-info/METADATA
print_libs-0.1.0.dist-info/WHEEL
print_libs-0.1.0.dist-info/top_level.txt
print_libs-0.1.0.dist-info/RECORD
