Metadata-Version: 2.1
Name: print_libs
Version: 0.1.0
Summary: 用于修饰输出
Home-page: https://github.com/your_user/your_project
Author: Z X H
Author-email: your_email@example.com
Classifier: Programming Language :: Python :: 3
Classifier: License :: OSI Approved :: MIT License
Classifier: Operating System :: OS Independent
Requires-Python: >=3.7
